fc_ims.py
fc_ims-3.0.dist-info/METADATA
fc_ims-3.0.dist-info/WHEEL
fc_ims-3.0.dist-info/top_level.txt
fc_ims-3.0.dist-info/RECORD
