Metadata-Version: 2.1
Name: fc-ims
Version: 3.0
Summary: 信息管理系统
Home-page: UNKNOWN
Author: fc
Author-email: fc@bigdata.com
License: UNKNOWN
Platform: UNKNOWN
